fastkit_core/__init__.py
fastkit_core/__version__.py
fastkit_core/config/__init__.py
fastkit_core/config/app.py
fastkit_core/config/database.py
fastkit_core/database/__init__.py
fastkit_core/database/async_repository.py
fastkit_core/database/base.py
fastkit_core/database/base_with_timestamps.py
fastkit_core/database/manager.py
fastkit_core/database/mixins.py
fastkit_core/database/repository.py
fastkit_core/database/session.py
fastkit_core/database/translatable.py
fastkit_core/http/__init__.py
fastkit_core/http/dependencies.py
fastkit_core/http/exception_handlers.py
fastkit_core/http/exceptions.py
fastkit_core/http/middleware.py
fastkit_core/http/responses.py
fastkit_core/i18n/__init__.py
fastkit_core/i18n/translation.py
fastkit_core/services/__init__.py
fastkit_core/services/async_base_crud_service.py
fastkit_core/services/base_crud_service.py
fastkit_core/services/slug_mixin_service.py
fastkit_core/validation/__init__.py
fastkit_core/validation/base.py
fastkit_core/validation/rules.py
fastkit_core/validation/validators.py
fastkit_core-0.3.4.dist-info/METADATA
fastkit_core-0.3.4.dist-info/WHEEL
fastkit_core-0.3.4.dist-info/top_level.txt
fastkit_core-0.3.4.dist-info/RECORD
