Metadata-Version: 2.4
Name: fastkit-core
Version: 0.3.4
Summary: FastKit Core is a lightweight toolkit that adds structure and common patterns to FastAPI.
Author-email: Codevelo <info@codevelo.io>
License: MIT
Project-URL: Homepage, https://github.com/codevelo-pub/fastkit-core/fastkit-core
Project-URL: Documentation, https://github.com/codevelo-pub/fastkit-core
Project-URL: Repository, https://github.com/codevelo-pub/fastkit-core
Project-URL: Issues, https://github.com/codevelo-pub/fastkit-core/issues
Keywords: fastapi,framework,toolkit,laravel,web,api,crud,database,orm
Classifier: Development Status :: 4 - Beta
Classifier: Intended Audience :: Developers
Classifier: License :: OSI Approved :: MIT License
Classifier: Programming Language :: Python :: 3
Classifier: Programming Language :: Python :: 3.11
Classifier: Programming Language :: Python :: 3.12
Classifier: Programming Language :: Python :: 3.13
Classifier: Framework :: FastAPI
Classifier: Topic :: Internet :: WWW/HTTP
Classifier: Topic :: Software Development :: Libraries :: Application Frameworks
Classifier: Topic :: Software Development :: Libraries :: Python Modules
Requires-Python: >=3.10
Requires-Dist: fastapi<0.116.0,>=0.115.0
Requires-Dist: uvicorn[standard]<0.35.0,>=0.34.0
Requires-Dist: pydantic<3.0.0,>=2.10.0
Requires-Dist: pydantic-settings<3.0.0,>=2.6.0
Requires-Dist: sqlalchemy<2.1.0,>=2.0.36
Requires-Dist: python-dotenv<2.0.0,>=1.0.0
Provides-Extra: dev
Requires-Dist: pytest>=8.3.0; extra == "dev"
Requires-Dist: pytest-cov>=6.0.0; extra == "dev"
Requires-Dist: pytest-asyncio>=0.24.0; extra == "dev"
Requires-Dist: ruff>=0.8.0; extra == "dev"
Requires-Dist: black>=24.10.0; extra == "dev"
Requires-Dist: isort>=5.13.0; extra == "dev"
Requires-Dist: mypy>=1.13.0; extra == "dev"
Provides-Extra: postgresql
Requires-Dist: psycopg2-binary>=2.9.10; extra == "postgresql"
Provides-Extra: mysql
Requires-Dist: pymysql>=1.1.0; extra == "mysql"
Requires-Dist: cryptography>=44.0.0; extra == "mysql"
Provides-Extra: mariadb
Requires-Dist: pymysql>=1.1.0; extra == "mariadb"
Requires-Dist: cryptography>=44.0.0; extra == "mariadb"
Provides-Extra: mssql
Requires-Dist: pyodbc>=5.2.0; extra == "mssql"
Provides-Extra: oracle
Requires-Dist: cx-Oracle>=8.3.0; extra == "oracle"
Provides-Extra: postgresql-async
Requires-Dist: asyncpg>=0.30.0; extra == "postgresql-async"
Provides-Extra: mysql-async
Requires-Dist: aiomysql>=0.2.0; extra == "mysql-async"
Requires-Dist: cryptography>=44.0.0; extra == "mysql-async"
Provides-Extra: mariadb-async
Requires-Dist: aiomysql>=0.2.0; extra == "mariadb-async"
Requires-Dist: cryptography>=44.0.0; extra == "mariadb-async"
Provides-Extra: mssql-async
Requires-Dist: aioodbc>=0.5.0; extra == "mssql-async"
Provides-Extra: oracle-async
Requires-Dist: oracledb>=2.5.0; extra == "oracle-async"
Provides-Extra: all-sync
Requires-Dist: psycopg2-binary>=2.9.10; extra == "all-sync"
Requires-Dist: pymysql>=1.1.0; extra == "all-sync"
Requires-Dist: pyodbc>=5.2.0; extra == "all-sync"
Requires-Dist: cx-Oracle>=8.3.0; extra == "all-sync"
Requires-Dist: cryptography>=44.0.0; extra == "all-sync"
Provides-Extra: all-async
Requires-Dist: asyncpg>=0.30.0; extra == "all-async"
Requires-Dist: aiomysql>=0.2.0; extra == "all-async"
Requires-Dist: aioodbc>=0.5.0; extra == "all-async"
Requires-Dist: oracledb>=2.5.0; extra == "all-async"
Requires-Dist: cryptography>=44.0.0; extra == "all-async"
Provides-Extra: all-drivers
Requires-Dist: psycopg2-binary>=2.9.10; extra == "all-drivers"
Requires-Dist: pymysql>=1.1.0; extra == "all-drivers"
Requires-Dist: pyodbc>=5.2.0; extra == "all-drivers"
Requires-Dist: cx-Oracle>=8.3.0; extra == "all-drivers"
Requires-Dist: asyncpg>=0.30.0; extra == "all-drivers"
Requires-Dist: aiomysql>=0.2.0; extra == "all-drivers"
Requires-Dist: aioodbc>=0.5.0; extra == "all-drivers"
Requires-Dist: oracledb>=2.5.0; extra == "all-drivers"
Requires-Dist: cryptography>=44.0.0; extra == "all-drivers"
Provides-Extra: docs
Requires-Dist: mkdocs>=1.6.0; extra == "docs"
Requires-Dist: mkdocs-material>=9.5.0; extra == "docs"
Requires-Dist: mkdocstrings[python]>=0.27.0; extra == "docs"
